README.md
setup.py
distributions_gb001/Binomialdistribution.py
distributions_gb001/Gaussiandistribution.py
distributions_gb001/Generaldistribution.py
distributions_gb001/__init__.py
distributions_gb001.egg-info/PKG-INFO
distributions_gb001.egg-info/SOURCES.txt
distributions_gb001.egg-info/dependency_links.txt
distributions_gb001.egg-info/not-zip-safe
distributions_gb001.egg-info/top_level.txt