Metadata-Version: 2.1
Name: distributions-gb001
Version: 1.0
Summary: Gaussian and binomial distributions
Home-page: UNKNOWN
Author: Abeeb Ridwan Olumide
Author-email: olumideuae@gmail.com
License: UNKNOWN
Platform: UNKNOWN
